symbolica_community-0.1.0.dist-info/METADATA
symbolica_community-0.1.0.dist-info/WHEEL
symbolica_community-0.1.0.dist-info/licenses/LICENSE
symbolica_community/examples/physics/tensors.py
symbolica_community/examples/physics/vakint.py
symbolica_community/__init__.py
symbolica_community/symbolica_community.pyi
symbolica_community/physics/__init__.py
symbolica_community/tensors.pyi
symbolica_community/py.typed
symbolica_community/symbolica_community.abi3.so
symbolica_community-0.1.0.dist-info/RECORD
