Metadata-Version: 2.3
Name: symbolica-community
Version: 0.1.0
Classifier: Programming Language :: Rust
Classifier: Programming Language :: Python :: Implementation :: CPython
Classifier: Programming Language :: Python :: Implementation :: PyPy
Requires-Dist: pytest ; extra == 'tests'
Provides-Extra: tests
License-File: LICENSE
Summary: Community-enhanced version of Symbolica: a blazing fast computer algebra system
Keywords: math,algebra,polynomial,expression,manipulation
Author: Ben Ruijl, Lucien Huber, Valentin Hischi
Author-email: benruyl@gmail.com, mail@lucien.ch, valentin.hirschi@gmail.com
License: MIT
Requires-Python: >=3.7
Project-URL: Source Code, https://github.com/benruijl/symbolica-community
